dijkstra/__init__.py
dijkstra/main.py
dijkstra/classes/__init__.py
dijkstra/classes/graph/__init__.py
dijkstra/classes/graph/graph.py
dijkstra/classes/solver/__init__.py
dijkstra/classes/solver/algo.py
dijkstra_solver-0.1.0.dist-info/LICENSE
dijkstra_solver-0.1.0.dist-info/METADATA
dijkstra_solver-0.1.0.dist-info/WHEEL
dijkstra_solver-0.1.0.dist-info/top_level.txt
dijkstra_solver-0.1.0.dist-info/RECORD
