Metadata-Version: 2.1
Name: dijkstra-solver
Version: 0.1.0
Summary: A Python implementation of Dijkstra's algorithm for finding the shortest path in a weighted graph.
Home-page: https://github.com/h471x/dijkstra_solver
Author: Hatix Ntsoa
Author-email: hatixntsoa@gmail.com
License: MIT
Classifier: Programming Language :: Python :: 3
Classifier: License :: OSI Approved :: MIT License
Classifier: Operating System :: OS Independent
License-File: LICENSE
